LICENSE.txt
MANIFEST.in
README.rst
setup.py
dirty_water/__init__.py
dirty_water/helpers.py
dirty_water/protocols.py
dirty_water/reaction.py
dirty_water.egg-info/PKG-INFO
dirty_water.egg-info/SOURCES.txt
dirty_water.egg-info/dependency_links.txt
dirty_water.egg-info/not-zip-safe
dirty_water.egg-info/requires.txt
dirty_water.egg-info/top_level.txt
docs/Makefile
docs/conf.py
docs/index.rst
tests/.coverage
tests/.coveragerc
tests/10_test_helpers.py
tests/30_test_protocols.py
tests/pytest.ini
tests/quick_test.py
tests/.cache/v/cache/lastfailed
tests/htmlcov/_home_kale_research_software_libraries_dirty_water_dirty_water___init___py.html
tests/htmlcov/_home_kale_research_software_libraries_dirty_water_dirty_water_helpers_py.html
tests/htmlcov/_home_kale_research_software_libraries_dirty_water_dirty_water_protocol_py.html
tests/htmlcov/_home_kale_research_software_libraries_dirty_water_dirty_water_protocols_py.html
tests/htmlcov/_home_kale_research_software_libraries_dirty_water_dirty_water_reaction_py.html
tests/htmlcov/coverage_html.js
tests/htmlcov/index.html
tests/htmlcov/jquery.debounce.min.js
tests/htmlcov/jquery.hotkeys.js
tests/htmlcov/jquery.isonscreen.js
tests/htmlcov/jquery.min.js
tests/htmlcov/jquery.tablesorter.min.js
tests/htmlcov/keybd_closed.png
tests/htmlcov/keybd_open.png
tests/htmlcov/status.json
tests/htmlcov/style.css