Metadata-Version: 1.1
Name: dirty-water
Version: 1.0.1
Summary: UNKNOWN
Home-page: https://github.com/kalekundert/dirty_water
Author: Kale Kundert
Author-email: kale.kundert@ucsf.edu
License: MIT
Keywords: dirty_water
Platform: UNKNOWN
Classifier: Development Status :: 2 - Pre-Alpha
Classifier: Intended Audience :: Developers
Classifier: License :: OSI Approved :: MIT License
Classifier: Natural Language :: English
Classifier: Programming Language :: Python :: 3
Classifier: Topic :: Software Development :: Libraries
